{"spec":1,"name":"Sora","previewText":"SORA is a typeface family commissioned for the SORA decentralized autonomous economy as a custom solution for branding and interface design. SORA, meaning sky in Japanese, is focused on empowering projects that benefit society by delivering new goods and services","main":{"ABCGintoNord-ExtraBold":"https://st.1001fonts.net/download/font/sora.extrabold.ttf","ggsans-Bold":"https://st.1001fonts.net/download/font/sora.bold.ttf","ggsans-BoldItalic":"https://st.1001fonts.net/download/font/sora.bold-italic.ttf","ggsans-ExtraBold":"https://st.1001fonts.net/download/font/sora.extrabold.ttf","ggsans-ExtraBoldItalic":"https://st.1001fonts.net/download/font/sora.extrabold-italic.ttf","ggsans-Medium":"https://st.1001fonts.net/download/font/sora.medium.ttf","ggsans-MediumItalic":"https://st.1001fonts.net/download/font/sora.medium-italic.ttf","ggsans-Normal":"https://st.1001fonts.net/download/font/sora.regular.ttf","ggsans-NormalItalic":"https://st.1001fonts.net/download/font/sora.italic.ttf","ggsans-Semibold":"https://st.1001fonts.net/download/font/sora.semibold.ttf","ggsans-SemiboldItalic":"https://st.1001fonts.net/download/font/sora.semibold-italic.ttf","NotoSans-Bold":"https://st.1001fonts.net/download/font/sora.bold.ttf","NotoSans-ExtraBold":"https://st.1001fonts.net/download/font/sora.extrabold.ttf","NotoSans-Medium":"https://st.1001fonts.net/download/font/sora.medium.ttf","NotoSans-Normal":"https://st.1001fonts.net/download/font/sora.regular.ttf","NotoSans-NormalItalic":"https://st.1001fonts.net/download/font/sora.italic.ttf","NotoSans-Semibold":"https://st.1001fonts.net/download/font/sora.semibold.ttf","SourceCodePro-Semibold":"https://st.1001fonts.net/download/font/sora.semibold.ttf"}}